{
    "name": "pxt-ledring",
    "description": "",
    "dependencies": {
        "core": "*",
        "radio": "*",
        "microphone": "*",
        "pxt-color": "github:CBurg-College/pxt-color#60e49e02fd91f1d38bbc793b4ffb74596afbb5c2"
    },
    "files": [
        "main.blocks",
        "main.ts",
        "README.md"
    ],
    "testFiles": [
        "test.ts"
    ],
    "targetVersions": {
        "target": "8.0.11",
        "targetId": "microbit"
    },
    "supportedTargets": [
        "microbit"
    ],
    "preferredEditor": "tsprj"
}
